gh_task/__init__.py
gh_task/__main__.py
gh_task/cli.py
gh_task/errors.py
gh_task/github.py
gh_task/project.py
gh_task-0.1.7.dist-info/licenses/LICENSE
gh_task-0.1.7.dist-info/METADATA
gh_task-0.1.7.dist-info/WHEEL
gh_task-0.1.7.dist-info/entry_points.txt
gh_task-0.1.7.dist-info/top_level.txt
gh_task-0.1.7.dist-info/RECORD
