Metadata-Version: 2.4
Name: gh-task
Version: 0.1.7
Summary: Python + CLI helpers for GitHub Projects task ownership
Author: yieldthought
License: MIT
Requires-Python: >=3.9
License-File: LICENSE
Requires-Dist: requests>=2.31
Dynamic: license-file
